LICENSE
MANIFEST.in
README.md
requirements.txt
setup.py
mindsdb_sdk/__about__.py
mindsdb_sdk/__init__.py
mindsdb_sdk/agents.py
mindsdb_sdk/config.py
mindsdb_sdk/connect.py
mindsdb_sdk/databases.py
mindsdb_sdk/handlers.py
mindsdb_sdk/jobs.py
mindsdb_sdk/knowledge_bases.py
mindsdb_sdk/ml_engines.py
mindsdb_sdk/models.py
mindsdb_sdk/projects.py
mindsdb_sdk/query.py
mindsdb_sdk/server.py
mindsdb_sdk/skills.py
mindsdb_sdk/tables.py
mindsdb_sdk/tree.py
mindsdb_sdk/views.py
mindsdb_sdk.egg-info/PKG-INFO
mindsdb_sdk.egg-info/SOURCES.txt
mindsdb_sdk.egg-info/dependency_links.txt
mindsdb_sdk.egg-info/requires.txt
mindsdb_sdk.egg-info/top_level.txt
mindsdb_sdk/connectors/__init__.py
mindsdb_sdk/connectors/rest_api.py
mindsdb_sdk/utils/__init__.py
mindsdb_sdk/utils/agents.py
mindsdb_sdk/utils/context.py
mindsdb_sdk/utils/mind.py
mindsdb_sdk/utils/objects_collection.py
mindsdb_sdk/utils/openai.py
mindsdb_sdk/utils/sql.py
mindsdb_sdk/utils/table_schema.py