Metadata-Version: 2.4
Name: mindsdb_sdk
Version: 3.4.9
Summary: MindsDB Python SDK, provides an SDK to use a remote mindsdb instance
Home-page: https://github.com/mindsdb/mindsdb_python_sdk
Download-URL: https://pypi.org/project/mindsdb-sdk/
Author: MindsDB Inc
Author-email: jorge@mindsdb.com
License: MIT
Classifier: Programming Language :: Python :: 3
Classifier: License :: OSI Approved :: MIT License
Classifier: Operating System :: OS Independent
Requires-Python: >=3.6
License-File: LICENSE
Requires-Dist: requests
Requires-Dist: pandas>=1.3.5
Requires-Dist: mindsdb-sql-parser==0.10.0
Requires-Dist: docstring-parser>=0.7.3
Requires-Dist: tenacity>=8.0.1
Requires-Dist: openai>=1.74.1
Requires-Dist: sseclient-py>=1.8.0
Requires-Dist: validators==0.20.0
Provides-Extra: dev
Requires-Dist: pytest; extra == "dev"
Dynamic: author
Dynamic: author-email
Dynamic: classifier
Dynamic: description
Dynamic: description-content-type
Dynamic: download-url
Dynamic: home-page
Dynamic: license
Dynamic: license-file
Dynamic: provides-extra
Dynamic: requires-dist
Dynamic: requires-python
Dynamic: summary
